Metadata-Version: 2.1
Name: cornea
Version: 1.0.0
Summary: A PyPI package to extract insightful information about an image using Machine Intelligence
Home-page: https://github.com/pravinba9495/cornea
Author: Praveen Ravichandran
Author-email: pravinba9495@gmail.com
License: MIT
Keywords: python,image-classification,pip,pypi-package,cognitive-services,microsoft-azure,image-analysis
Platform: UNKNOWN
Requires-Python: ~=3.7
